frplib/__about__.py
frplib/__init__.py
frplib/__main__.py
frplib/calculate.py
frplib/env.py
frplib/exceptions.py
frplib/expectations.py
frplib/extras.py
frplib/frps.py
frplib/kind_trees.py
frplib/kinds.py
frplib/market.py
frplib/numeric.py
frplib/output.py
frplib/protocols.py
frplib/py.typed
frplib/quantity.py
frplib/statistics.py
frplib/symbolic.py
frplib/utils.py
frplib/vec_tuples.py
frplib/cli/__init__.py
frplib/data/__init__.py
frplib/data/google-books-common-words.txt
frplib/data/make_words.py
frplib/data/market-help-buy.txt
frplib/data/market-help-compare.txt
frplib/data/market-help-demo.txt
frplib/data/market-help-exit.txt
frplib/data/market-help-help.txt
frplib/data/market-help-kinds.txt
frplib/data/market-help-overview.txt
frplib/data/market-help-show.txt
frplib/data/words.py
frplib/data/playground-help/actions.md
frplib/data/playground-help/frp-combinators.md
frplib/data/playground-help/frp-factories.md
frplib/data/playground-help/frps.md
frplib/data/playground-help/kind-combinators.md
frplib/data/playground-help/kind-factories.md
frplib/data/playground-help/kinds.md
frplib/data/playground-help/modules.md
frplib/data/playground-help/numerics.md
frplib/data/playground-help/object-index.md
frplib/data/playground-help/overview.md
frplib/data/playground-help/projections.md
frplib/data/playground-help/statistic-builtins.md
frplib/data/playground-help/statistic-combinators.md
frplib/data/playground-help/statistic-factories.md
frplib/data/playground-help/statistics-builtins.md
frplib/data/playground-help/statistics-combinators.md
frplib/data/playground-help/statistics-factories.md
frplib/data/playground-help/statistics.md
frplib/data/playground-help/topics.md
frplib/data/playground-help/utilities.md
frplib/data/playground-help/kind-combinators/bin.md
frplib/data/playground-help/kind-combinators/fast_mixture_pow.md
frplib/data/playground-help/kind-factories/binary.md
frplib/data/playground-help/kind-factories/constant.md
frplib-0.2.11.dist-info/METADATA
frplib-0.2.11.dist-info/WHEEL
frplib-0.2.11.dist-info/entry_points.txt
frplib-0.2.11.dist-info/licenses/LICENSE
frplib-0.2.11.dist-info/RECORD
