Metadata-Version: 2.4
Name: frplib
Version: 0.2.11
Summary: A library for building, manipulating, and calculating with FRPs and their kinds, and an executable application for sampling large collections of FRPs of an arbitrary kind. This is primarily designed for instructional purposes in the teaching of probability theory and statistical modeling.
Project-URL: Homepage, https://github.com/genovese/frplib
Project-URL: Documentation, https://github.com/genovese/frplib#readme
Project-URL: Issues, https://github.com/genovese/frplib/issues
Project-URL: Source, https://github.com/genovese/frplib
Author-email: "Christopher R. Genovese" <genovese@cmu.edu>
License:                     GNU AFFERO GENERAL PUBLIC LICENSE
License-File: LICENSE
Keywords: instruction,probability,statistics
Classifier: Development Status :: 4 - Beta
Classifier: Programming Language :: Python
Classifier: Programming Language :: Python :: 3.9
Classifier: Programming Language :: Python :: 3.10
Classifier: Programming Language :: Python :: 3.11
Classifier: Programming Language :: Python :: 3.12
Classifier: Programming Language :: Python :: 3.13
Classifier: Programming Language :: Python :: Implementation :: CPython
Classifier: Programming Language :: Python :: Implementation :: PyPy
Requires-Python: >=3.9
Requires-Dist: click>=8.1.4
Requires-Dist: numpy>=1.25.2
Requires-Dist: parsy>=2.1
Requires-Dist: pillow>=10.1
Requires-Dist: prompt-toolkit>=3.0.36
Requires-Dist: ptpython==3.0.23
Requires-Dist: pygments>=2.12.0
Requires-Dist: rich>=13.3.2
Requires-Dist: scipy>=1.13.0
Requires-Dist: typing-extensions>=4.5.0
Provides-Extra: dev
Requires-Dist: black; extra == 'dev'
Requires-Dist: hypothesis; extra == 'dev'
Requires-Dist: pytest; extra == 'dev'
Requires-Dist: returns; extra == 'dev'
Requires-Dist: ruff; extra == 'dev'
